unsplash_get/__init__.py
unsplash_get/__main__.py
unsplash_get/unsplash_get.py
unsplash_get-0.1.2.dist-info/LICENSE.txt
unsplash_get-0.1.2.dist-info/METADATA
unsplash_get-0.1.2.dist-info/WHEEL
unsplash_get-0.1.2.dist-info/entry_points.txt
unsplash_get-0.1.2.dist-info/top_level.txt
unsplash_get-0.1.2.dist-info/RECORD
