Metadata-Version: 2.1
Name: unsplash-get
Version: 0.1.2
Summary: unsplash srape tool
Home-page: https://github.com/streanger/unsplash_get
Author: streanger
Author-email: divisionexe@gmail.com
License: MIT
Keywords: unsplash scrape stock images
Classifier: Programming Language :: Python :: 3
Classifier: License :: OSI Approved :: MIT License
Classifier: Operating System :: OS Independent
License-File: LICENSE.txt
Requires-Dist: requests
Requires-Dist: lxml
Requires-Dist: beautifulsoup4
